drawio_agents/VERSION
drawio_agents/__init__.py
drawio_agents-0.0.1.dist-info/LICENSE
drawio_agents-0.0.1.dist-info/METADATA
drawio_agents-0.0.1.dist-info/WHEEL
drawio_agents-0.0.1.dist-info/RECORD
